pygeodiff/__about__.py
pygeodiff/__init__.py
pygeodiff/geodifflib.py
pygeodiff/libpygeodiff-2.1.2-python.so
pygeodiff/main.py
pygeodiff.libs/libgcc_s-0cd532bd.so.1
pygeodiff.libs/libsqlite3-11cef46f.so.3.49.2
pygeodiff.libs/libstdc++-5d72f927.so.6.0.33
pygeodiff-2.1.2.dist-info/METADATA
pygeodiff-2.1.2.dist-info/WHEEL
pygeodiff-2.1.2.dist-info/entry_points.txt
pygeodiff-2.1.2.dist-info/top_level.txt
pygeodiff-2.1.2.dist-info/RECORD
pygeodiff-2.1.2.dist-info/licenses/LICENSE
pygeodiff-2.1.2.dist-info/sboms/auditwheel.cdx.json
