Metadata-Version: 2.1
Name: pygeodiff
Version: 2.1.2
Summary: Python wrapper around GeoDiff library
Home-page: https://github.com/MerginMaps/geodiff
Author: Lutra Consulting Ltd.
Author-email: info@merginmaps.com
License: License :: OSI Approved :: MIT License
Keywords: diff,gis,geo,geopackage,merge
Classifier: Programming Language :: Python :: 3
Requires-Python: >=3.7
License-File: LICENSE
